{"stats":{"minecraft:picked_up":{"minecraft:birch_log":1,"minecraft:dirt":14},"minecraft:custom":{"minecraft:jump":88,"minecraft:damage_taken":983,"minecraft:walk_one_cm":13270,"minecraft:damage_dealt":64,"minecraft:crouch_one_cm":99,"minecraft:leave_game":6,"minecraft:sprint_one_cm":34833,"minecraft:play_time":66843,"minecraft:time_since_death":29038,"minecraft:walk_on_water_one_cm":2058,"minecraft:deaths":4,"minecraft:sneak_time":9,"minecraft:total_world_time":66843,"minecraft:fall_one_cm":3244,"minecraft:fly_one_cm":23109,"minecraft:time_since_rest":41679},"minecraft:used":{"minecraft:birch_log":1,"minecraft:dirt":14},"minecraft:mined":{"minecraft:birch_log":1},"minecraft:killed_by":{"minecraft:zombie":4}},"DataVersion":4189}